list_sync/connector/__init__.py
list_sync/connector/base_connector.py
list_sync/connector/mysql_connector.py
list_sync/connector/pgsql_connector.py
list_sync/connector/producer/__init__.py
list_sync/connector/producer/producer.py
list_sync/consumer/__init__.py
list_sync/consumer/consumer.py
list_sync/consumer/writer/__init__.py
list_sync/consumer/writer/csv_writer.py
list_sync-0.1.0.dist-info/METADATA
list_sync-0.1.0.dist-info/WHEEL
list_sync-0.1.0.dist-info/RECORD
