Metadata-Version: 2.3
Name: list_sync
Version: 0.1.0
Summary: list_sync is a Python-based system designed for Change Data Capture (CDC) from relational databases to Apache Kafka. It supports both MySQL and PostgreSQL as data sources, providing real-time streaming of database changes through a distributed system architecture while maintaining data consistency and fault tolerance.
Author: Stefano Babini
Author-email: stefano.babini5@studio.unibo.it
Requires-Python: >=3.12,<3.13
Classifier: Programming Language :: Python :: 3
Classifier: Programming Language :: Python :: 3.12
Requires-Dist: confluent-kafka (>=2.8.0,<3.0.0)
Requires-Dist: mysql-connector-python (>=9.1.0,<9.2.0)
Requires-Dist: mysql-replication (>=1.0.9,<2.0.0)
Requires-Dist: psycopg2-binary (>=2.9.10,<3.0.0)
